slack_webhook_notifier/__init__.py
slack_webhook_notifier/main.py
slack_webhook_notifier/py.typed
slack_webhook_notifier-2.0.7.dist-info/licenses/LICENSE
slack_webhook_notifier-2.0.7.dist-info/METADATA
slack_webhook_notifier-2.0.7.dist-info/WHEEL
slack_webhook_notifier-2.0.7.dist-info/top_level.txt
slack_webhook_notifier-2.0.7.dist-info/RECORD
