Metadata-Version: 2.4
Name: slack-webhook-notifier
Version: 2.0.7
Summary: This package helps monitor automation processes with real-time updates directly in Slack.
Author-email: Mark Moreno <mark@securehst.com>
License: MIT
Project-URL: Bug Tracker, https://github.com/markm-io/slack-webhook-notifier/issues
Project-URL: Changelog, https://github.com/markm-io/slack-webhook-notifier/blob/main/CHANGELOG.md
Project-URL: documentation, https://slack-webhook-notifier.readthedocs.io
Project-URL: repository, https://github.com/markm-io/slack-webhook-notifier
Classifier: Development Status :: 2 - Pre-Alpha
Classifier: Intended Audience :: Developers
Classifier: Natural Language :: English
Classifier: Operating System :: OS Independent
Classifier: Programming Language :: Python :: 3.9
Classifier: Programming Language :: Python :: 3.10
Classifier: Programming Language :: Python :: 3.11
Classifier: Programming Language :: Python :: 3.12
Classifier: Programming Language :: Python :: 3.13
Classifier: Topic :: Software Development :: Libraries
Requires-Python: >=3.9
License-File: LICENSE
Requires-Dist: requests>=2.32.3
Dynamic: license-file
